CHANGELOG
LICENSE
MANIFEST.in
README.rst
setup.cfg
setup.py
tangled.site.egg-info/PKG-INFO
tangled.site.egg-info/SOURCES.txt
tangled.site.egg-info/dependency_links.txt
tangled.site.egg-info/entry_points.txt
tangled.site.egg-info/requires.txt
tangled.site.egg-info/top_level.txt
tangled/site/__init__.py
tangled/site/auth.py
tangled/site/command.py
tangled/site/defaults.ini
tangled/site/model/__init__.py
tangled/site/model/base.py
tangled/site/model/entry.py
tangled/site/model/user.py
tangled/site/resources/__init__.py
tangled/site/resources/admin.py
tangled/site/resources/auth.py
tangled/site/resources/entry.py
tangled/site/resources/error.py
tangled/site/resources/home.py
tangled/site/resources/user.py
tangled/site/tests/__init__.py
tangled/site/tests/tests.py
tangled/site/themes/default/.DS_Store
tangled/site/themes/default/static/.DS_Store
tangled/site/themes/default/static/main.css
tangled/site/themes/default/templates/base.mako
tangled/site/themes/default/templates/error.mako
tangled/site/themes/default/templates/profile.mako
tangled/site/themes/default/templates/admin/base.mako
tangled/site/themes/default/templates/admin/index.mako
tangled/site/themes/default/templates/admin/meta.mako
tangled/site/themes/default/templates/admin/users.mako
tangled/site/themes/default/templates/auth/sign-in.mako
tangled/site/themes/default/templates/auth/sign-out-form.mako
tangled/site/themes/default/templates/auth/sign-up.mako
tangled/site/themes/default/templates/entry/base.mako
tangled/site/themes/default/templates/entry/edit.mako
tangled/site/themes/default/templates/entry/entries.mako
tangled/site/themes/default/templates/entry/entry.mako
tangled/site/themes/default/templates/entry/new.mako